{"weekStart": "2026-07-06", "weekEnd": "2026-07-12", "pines": [{"dow": 1, "hour": 20, "units": 14}, {"dow": 3, "hour": 8, "units": 18}, {"dow": 5, "hour": 16, "units": 33}, {"dow": 3, "hour": 11, "units": 27}, {"dow": 5, "hour": 19, "units": 15}, {"dow": 4, "hour": 7, "units": 15}, {"dow": 6, "hour": 15, "units": 34}, {"dow": 0, "hour": 11, "units": 25}, {"dow": 6, "hour": 18, "units": 6}, {"dow": 4, "hour": 10, "units": 26}, {"dow": 2, "hour": 19, "units": 10}, {"dow": 0, "hour": 14, "units": 10}, {"dow": 1, "hour": 13, "units": 11}, {"dow": 1, "hour": 7, "units": 12}, {"dow": 3, "hour": 18, "units": 22}, {"dow": 1, "hour": 10, "units": 10}, {"dow": 5, "hour": 9, "units": 13}, {"dow": 6, "hour": 8, "units": 11}, {"dow": 4, "hour": 20, "units": 14}, {"dow": 2, "hour": 12, "units": 36}, {"dow": 4, "hour": 17, "units": 19}, {"dow": 2, "hour": 9, "units": 18}, {"dow": 4, "hour": 18, "units": 24}, {"dow": 0, "hour": 19, "units": 11}, {"dow": 4, "hour": 15, "units": 17}, {"dow": 4, "hour": 9, "units": 28}, {"dow": 0, "hour": 13, "units": 35}, {"dow": 0, "hour": 16, "units": 29}, {"dow": 6, "hour": 20, "units": 19}, {"dow": 4, "hour": 12, "units": 32}, {"dow": 5, "hour": 17, "units": 21}, {"dow": 1, "hour": 18, "units": 8}, {"dow": 1, "hour": 15, "units": 9}, {"dow": 5, "hour": 8, "units": 24}, {"dow": 5, "hour": 14, "units": 28}, {"dow": 1, "hour": 12, "units": 43}, {"dow": 5, "hour": 11, "units": 38}, {"dow": 6, "hour": 10, "units": 18}, {"dow": 2, "hour": 11, "units": 28}, {"dow": 2, "hour": 14, "units": 22}, {"dow": 6, "hour": 13, "units": 15}, {"dow": 6, "hour": 16, "units": 28}, {"dow": 2, "hour": 17, "units": 13}, {"dow": 3, "hour": 10, "units": 14}, {"dow": 3, "hour": 19, "units": 36}, {"dow": 2, "hour": 20, "units": 12}, {"dow": 3, "hour": 13, "units": 45}, {"dow": 3, "hour": 16, "units": 28}, {"dow": 2, "hour": 15, "units": 20}, {"dow": 0, "hour": 10, "units": 20}, {"dow": 3, "hour": 14, "units": 42}, {"dow": 6, "hour": 17, "units": 21}, {"dow": 2, "hour": 18, "units": 11}, {"dow": 1, "hour": 9, "units": 19}, {"dow": 3, "hour": 17, "units": 32}, {"dow": 4, "hour": 13, "units": 37}, {"dow": 3, "hour": 20, "units": 13}, {"dow": 4, "hour": 16, "units": 31}, {"dow": 0, "hour": 17, "units": 16}, {"dow": 2, "hour": 8, "units": 15}, {"dow": 5, "hour": 12, "units": 31}, {"dow": 4, "hour": 19, "units": 23}, {"dow": 5, "hour": 15, "units": 32}, {"dow": 6, "hour": 14, "units": 21}, {"dow": 1, "hour": 16, "units": 13}, {"dow": 3, "hour": 7, "units": 17}, {"dow": 5, "hour": 18, "units": 23}, {"dow": 6, "hour": 11, "units": 39}, {"dow": 1, "hour": 19, "units": 6}, {"dow": 1, "hour": 11, "units": 17}, {"dow": 6, "hour": 9, "units": 13}, {"dow": 1, "hour": 17, "units": 24}, {"dow": 2, "hour": 7, "units": 29}, {"dow": 1, "hour": 14, "units": 18}, {"dow": 5, "hour": 13, "units": 48}, {"dow": 2, "hour": 13, "units": 14}, {"dow": 6, "hour": 12, "units": 54}, {"dow": 5, "hour": 20, "units": 27}, {"dow": 2, "hour": 16, "units": 11}, {"dow": 2, "hour": 10, "units": 30}, {"dow": 4, "hour": 21, "units": 2}, {"dow": 3, "hour": 9, "units": 14}, {"dow": 3, "hour": 12, "units": 42}, {"dow": 6, "hour": 19, "units": 7}, {"dow": 3, "hour": 15, "units": 29}, {"dow": 4, "hour": 8, "units": 13}, {"dow": 0, "hour": 12, "units": 37}, {"dow": 4, "hour": 11, "units": 32}, {"dow": 5, "hour": 10, "units": 24}, {"dow": 0, "hour": 9, "units": 16}, {"dow": 0, "hour": 15, "units": 20}, {"dow": 1, "hour": 8, "units": 9}, {"dow": 0, "hour": 18, "units": 10}, {"dow": 5, "hour": 7, "units": 12}, {"dow": 4, "hour": 14, "units": 33}], "miramar": [{"dow": 2, "hour": 19, "units": 16}, {"dow": 3, "hour": 12, "units": 39}, {"dow": 6, "hour": 18, "units": 13}, {"dow": 3, "hour": 15, "units": 37}, {"dow": 1, "hour": 7, "units": 12}, {"dow": 3, "hour": 18, "units": 42}, {"dow": 4, "hour": 11, "units": 33}, {"dow": 0, "hour": 15, "units": 21}, {"dow": 4, "hour": 14, "units": 29}, {"dow": 5, "hour": 10, "units": 42}, {"dow": 5, "hour": 16, "units": 31}, {"dow": 0, "hour": 18, "units": 12}, {"dow": 4, "hour": 17, "units": 25}, {"dow": 4, "hour": 20, "units": 18}, {"dow": 5, "hour": 13, "units": 1}, {"dow": 1, "hour": 14, "units": 24}, {"dow": 5, "hour": 19, "units": 21}, {"dow": 6, "hour": 12, "units": 22}, {"dow": 2, "hour": 13, "units": 27}, {"dow": 1, "hour": 17, "units": 10}, {"dow": 6, "hour": 15, "units": 40}, {"dow": 2, "hour": 16, "units": 22}, {"dow": 6, "hour": 9, "units": 12}, {"dow": 1, "hour": 20, "units": 7}, {"dow": 6, "hour": 10, "units": 35}, {"dow": 4, "hour": 19, "units": 38}, {"dow": 1, "hour": 15, "units": 14}, {"dow": 2, "hour": 8, "units": 12}, {"dow": 1, "hour": 12, "units": 42}, {"dow": 6, "hour": 1, "units": 1}, {"dow": 3, "hour": 10, "units": 48}, {"dow": 2, "hour": 11, "units": 33}, {"dow": 5, "hour": 18, "units": 26}, {"dow": 2, "hour": 14, "units": 18}, {"dow": 3, "hour": 7, "units": 13}, {"dow": 4, "hour": 22, "units": 1}, {"dow": 0, "hour": 10, "units": 20}, {"dow": 4, "hour": 9, "units": 16}, {"dow": 6, "hour": 20, "units": 14}, {"dow": 6, "hour": 17, "units": 11}, {"dow": 3, "hour": 13, "units": 45}, {"dow": 0, "hour": 16, "units": 25}, {"dow": 1, "hour": 9, "units": 9}, {"dow": 3, "hour": 20, "units": 21}, {"dow": 5, "hour": 8, "units": 8}, {"dow": 0, "hour": 13, "units": 39}, {"dow": 5, "hour": 11, "units": 32}, {"dow": 4, "hour": 12, "units": 46}, {"dow": 5, "hour": 17, "units": 12}, {"dow": 5, "hour": 14, "units": 40}, {"dow": 5, "hour": 20, "units": 30}, {"dow": 3, "hour": 9, "units": 23}, {"dow": 1, "hour": 18, "units": 12}, {"dow": 6, "hour": 16, "units": 14}, {"dow": 0, "hour": 12, "units": 30}, {"dow": 2, "hour": 17, "units": 7}, {"dow": 2, "hour": 20, "units": 12}, {"dow": 4, "hour": 8, "units": 25}, {"dow": 6, "hour": 13, "units": 34}, {"dow": 6, "hour": 19, "units": 8}, {"dow": 0, "hour": 9, "units": 2}, {"dow": 3, "hour": 16, "units": 27}, {"dow": 1, "hour": 11, "units": 25}, {"dow": 1, "hour": 8, "units": 12}, {"dow": 3, "hour": 19, "units": 21}, {"dow": 5, "hour": 7, "units": 12}, {"dow": 4, "hour": 21, "units": 4}, {"dow": 4, "hour": 15, "units": 27}, {"dow": 2, "hour": 7, "units": 13}, {"dow": 2, "hour": 10, "units": 11}, {"dow": 4, "hour": 18, "units": 29}, {"dow": 0, "hour": 19, "units": 8}, {"dow": 4, "hour": 7, "units": 11}, {"dow": 0, "hour": 14, "units": 22}, {"dow": 5, "hour": 6, "units": 2}, {"dow": 4, "hour": 13, "units": 36}, {"dow": 0, "hour": 11, "units": 30}, {"dow": 0, "hour": 17, "units": 19}, {"dow": 4, "hour": 10, "units": 34}, {"dow": 4, "hour": 16, "units": 33}, {"dow": 1, "hour": 13, "units": 17}, {"dow": 1, "hour": 19, "units": 20}, {"dow": 5, "hour": 9, "units": 18}, {"dow": 1, "hour": 16, "units": 11}, {"dow": 5, "hour": 15, "units": 22}, {"dow": 1, "hour": 10, "units": 31}, {"dow": 6, "hour": 14, "units": 24}, {"dow": 2, "hour": 15, "units": 29}, {"dow": 2, "hour": 9, "units": 19}, {"dow": 6, "hour": 8, "units": 9}, {"dow": 2, "hour": 18, "units": 29}, {"dow": 6, "hour": 11, "units": 19}, {"dow": 2, "hour": 12, "units": 24}, {"dow": 3, "hour": 14, "units": 29}, {"dow": 3, "hour": 8, "units": 16}, {"dow": 3, "hour": 11, "units": 49}, {"dow": 3, "hour": 17, "units": 20}], "margate": [{"dow": 0, "hour": 13, "units": 29}, {"dow": 0, "hour": 19, "units": 12}, {"dow": 5, "hour": 8, "units": 9}, {"dow": 4, "hour": 15, "units": 19}, {"dow": 0, "hour": 16, "units": 9}, {"dow": 4, "hour": 12, "units": 24}, {"dow": 1, "hour": 18, "units": 8}, {"dow": 5, "hour": 14, "units": 10}, {"dow": 1, "hour": 15, "units": 9}, {"dow": 1, "hour": 12, "units": 12}, {"dow": 5, "hour": 11, "units": 22}, {"dow": 6, "hour": 10, "units": 22}, {"dow": 6, "hour": 13, "units": 38}, {"dow": 2, "hour": 14, "units": 15}, {"dow": 2, "hour": 17, "units": 7}, {"dow": 2, "hour": 11, "units": 8}, {"dow": 3, "hour": 10, "units": 13}, {"dow": 4, "hour": 9, "units": 6}, {"dow": 3, "hour": 13, "units": 27}, {"dow": 6, "hour": 20, "units": 10}, {"dow": 3, "hour": 16, "units": 18}, {"dow": 1, "hour": 20, "units": 13}, {"dow": 5, "hour": 19, "units": 14}, {"dow": 3, "hour": 8, "units": 29}, {"dow": 5, "hour": 16, "units": 18}, {"dow": 3, "hour": 11, "units": 27}, {"dow": 4, "hour": 7, "units": 8}, {"dow": 6, "hour": 15, "units": 7}, {"dow": 0, "hour": 11, "units": 24}, {"dow": 4, "hour": 10, "units": 15}, {"dow": 6, "hour": 18, "units": 12}, {"dow": 0, "hour": 14, "units": 24}, {"dow": 2, "hour": 19, "units": 6}, {"dow": 1, "hour": 7, "units": 5}, {"dow": 1, "hour": 13, "units": 23}, {"dow": 3, "hour": 18, "units": 25}, {"dow": 1, "hour": 10, "units": 10}, {"dow": 5, "hour": 9, "units": 13}, {"dow": 6, "hour": 8, "units": 6}, {"dow": 4, "hour": 20, "units": 3}, {"dow": 2, "hour": 12, "units": 20}, {"dow": 4, "hour": 17, "units": 18}, {"dow": 2, "hour": 9, "units": 10}, {"dow": 6, "hour": 12, "units": 12}, {"dow": 1, "hour": 14, "units": 18}, {"dow": 4, "hour": 18, "units": 13}, {"dow": 2, "hour": 10, "units": 9}, {"dow": 1, "hour": 17, "units": 5}, {"dow": 6, "hour": 9, "units": 7}, {"dow": 2, "hour": 7, "units": 1}, {"dow": 2, "hour": 13, "units": 26}, {"dow": 5, "hour": 17, "units": 9}, {"dow": 3, "hour": 12, "units": 23}, {"dow": 2, "hour": 16, "units": 10}, {"dow": 5, "hour": 20, "units": 2}, {"dow": 3, "hour": 9, "units": 18}, {"dow": 0, "hour": 12, "units": 35}, {"dow": 4, "hour": 14, "units": 22}, {"dow": 6, "hour": 19, "units": 8}, {"dow": 4, "hour": 11, "units": 22}, {"dow": 3, "hour": 15, "units": 29}, {"dow": 2, "hour": 20, "units": 5}, {"dow": 4, "hour": 8, "units": 15}, {"dow": 6, "hour": 16, "units": 15}, {"dow": 5, "hour": 13, "units": 24}, {"dow": 0, "hour": 15, "units": 14}, {"dow": 3, "hour": 19, "units": 7}, {"dow": 1, "hour": 11, "units": 7}, {"dow": 5, "hour": 10, "units": 18}, {"dow": 1, "hour": 8, "units": 7}, {"dow": 0, "hour": 18, "units": 13}, {"dow": 5, "hour": 7, "units": 5}, {"dow": 0, "hour": 10, "units": 7}, {"dow": 3, "hour": 17, "units": 12}, {"dow": 3, "hour": 14, "units": 18}, {"dow": 4, "hour": 16, "units": 28}, {"dow": 0, "hour": 17, "units": 13}, {"dow": 1, "hour": 9, "units": 15}, {"dow": 2, "hour": 8, "units": 10}, {"dow": 4, "hour": 19, "units": 19}, {"dow": 4, "hour": 13, "units": 16}, {"dow": 3, "hour": 20, "units": 8}, {"dow": 5, "hour": 15, "units": 8}, {"dow": 1, "hour": 16, "units": 4}, {"dow": 5, "hour": 12, "units": 24}, {"dow": 3, "hour": 7, "units": 5}, {"dow": 5, "hour": 18, "units": 15}, {"dow": 2, "hour": 18, "units": 20}, {"dow": 6, "hour": 17, "units": 6}, {"dow": 1, "hour": 19, "units": 4}, {"dow": 6, "hour": 11, "units": 15}, {"dow": 6, "hour": 14, "units": 16}, {"dow": 2, "hour": 15, "units": 13}]}